[
	{
		"inputs": [
			{
				"internalType": "address[]",
				"name": "assigned",
				"type": "address[]"
			},
			{
				"internalType": "uint256[]",
				"name": "_rate",
				"type": "uint256[]"
			}
		],
		"name": "addAllocationFundAddress",
		"outputs": [],
		"stateMutability": "nonpayable",
		"type": "function"
	},
	{
		"inputs": [],
		"name": "AllocationFund",
		"outputs": [],
		"stateMutability": "nonpayable",
		"type": "function"
	},
	{
		"inputs": [],
		"stateMutability": "nonpayable",
		"type": "constructor"
	},
	{
		"anonymous": false,
		"inputs": [
			{
				"indexed": true,
				"internalType": "address",
				"name": "previousOwner",
				"type": "address"
			},
			{
				"indexed": true,
				"internalType": "address",
				"name": "newOwner",
				"type": "address"
			}
		],
		"name": "OwnershipTransferred",
		"type": "event"
	},
	{
		"anonymous": false,
		"inputs": [
			{
				"indexed": false,
				"internalType": "uint256",
				"name": "num",
				"type": "uint256"
			},
			{
				"indexed": false,
				"internalType": "address",
				"name": "user",
				"type": "address"
			},
			{
				"indexed": false,
				"internalType": "uint256",
				"name": "amount",
				"type": "uint256"
			}
		],
		"name": "incomeRecord",
		"type": "event"
	},
	{
		"inputs": [
			{
				"internalType": "address",
				"name": "_addr",
				"type": "address"
			}
		],
		"name": "removeAddr",
		"outputs": [],
		"stateMutability": "nonpayable",
		"type": "function"
	},
	{
		"inputs": [],
		"name": "renounceOwnership",
		"outputs": [],
		"stateMutability": "nonpayable",
		"type": "function"
	},
	{
		"inputs": [
			{
				"internalType": "uint256",
				"name": "_id",
				"type": "uint256"
			},
			{
				"internalType": "address",
				"name": "_addr",
				"type": "address"
			}
		],
		"name": "setAddr",
		"outputs": [],
		"stateMutability": "nonpayable",
		"type": "function"
	},
	{
		"inputs": [
			{
				"internalType": "address",
				"name": "_addr",
				"type": "address"
			},
			{
				"internalType": "bool",
				"name": "_status",
				"type": "bool"
			}
		],
		"name": "setAllowAddr",
		"outputs": [],
		"stateMutability": "nonpayable",
		"type": "function"
	},
	{
		"inputs": [
			{
				"internalType": "uint256",
				"name": "_award",
				"type": "uint256"
			}
		],
		"name": "setAward",
		"outputs": [],
		"stateMutability": "nonpayable",
		"type": "function"
	},
	{
		"inputs": [
			{
				"internalType": "address",
				"name": "_controlAddress",
				"type": "address"
			}
		],
		"name": "setControlAddress",
		"outputs": [],
		"stateMutability": "nonpayable",
		"type": "function"
	},
	{
		"inputs": [
			{
				"internalType": "uint256",
				"name": "_time",
				"type": "uint256"
			}
		],
		"name": "setIntervalTime",
		"outputs": [],
		"stateMutability": "nonpayable",
		"type": "function"
	},
	{
		"inputs": [
			{
				"internalType": "uint256",
				"name": "_rate",
				"type": "uint256"
			}
		],
		"name": "setRate",
		"outputs": [],
		"stateMutability": "nonpayable",
		"type": "function"
	},
	{
		"inputs": [
			{
				"internalType": "address",
				"name": "_Reputation",
				"type": "address"
			}
		],
		"name": "setReputation",
		"outputs": [],
		"stateMutability": "nonpayable",
		"type": "function"
	},
	{
		"inputs": [
			{
				"internalType": "uint256",
				"name": "_amount",
				"type": "uint256"
			}
		],
		"name": "setReputationAmount",
		"outputs": [],
		"stateMutability": "nonpayable",
		"type": "function"
	},
	{
		"inputs": [
			{
				"internalType": "uint256",
				"name": "num",
				"type": "uint256"
			},
			{
				"internalType": "address",
				"name": "user",
				"type": "address"
			},
			{
				"internalType": "uint256",
				"name": "amount",
				"type": "uint256"
			}
		],
		"name": "setSourceOfIncome",
		"outputs": [],
		"stateMutability": "nonpayable",
		"type": "function"
	},
	{
		"inputs": [],
		"name": "setStatus",
		"outputs": [],
		"stateMutability": "nonpayable",
		"type": "function"
	},
	{
		"inputs": [
			{
				"internalType": "address",
				"name": "_addr",
				"type": "address"
			},
			{
				"internalType": "uint256",
				"name": "_rate",
				"type": "uint256"
			}
		],
		"name": "setTotalDistributionRatio",
		"outputs": [],
		"stateMutability": "nonpayable",
		"type": "function"
	},
	{
		"inputs": [
			{
				"internalType": "uint256",
				"name": "_time",
				"type": "uint256"
			}
		],
		"name": "setUerIntverTime",
		"outputs": [],
		"stateMutability": "nonpayable",
		"type": "function"
	},
	{
		"inputs": [
			{
				"internalType": "address",
				"name": "_weth",
				"type": "address"
			}
		],
		"name": "setWeth",
		"outputs": [],
		"stateMutability": "nonpayable",
		"type": "function"
	},
	{
		"inputs": [
			{
				"internalType": "address",
				"name": "newOwner",
				"type": "address"
			}
		],
		"name": "transferOwnership",
		"outputs": [],
		"stateMutability": "nonpayable",
		"type": "function"
	},
	{
		"inputs": [],
		"name": "withdraw",
		"outputs": [],
		"stateMutability": "nonpayable",
		"type": "function"
	},
	{
		"inputs": [
			{
				"internalType": "uint256",
				"name": "",
				"type": "uint256"
			}
		],
		"name": "AllocationFundAddress",
		"outputs": [
			{
				"internalType": "address",
				"name": "",
				"type": "address"
			}
		],
		"stateMutability": "view",
		"type": "function"
	},
	{
		"inputs": [
			{
				"internalType": "address",
				"name": "",
				"type": "address"
			}
		],
		"name": "AllocationFundUserTime",
		"outputs": [
			{
				"internalType": "uint256",
				"name": "",
				"type": "uint256"
			}
		],
		"stateMutability": "view",
		"type": "function"
	},
	{
		"inputs": [
			{
				"internalType": "address",
				"name": "",
				"type": "address"
			}
		],
		"name": "allowAddr",
		"outputs": [
			{
				"internalType": "bool",
				"name": "",
				"type": "bool"
			}
		],
		"stateMutability": "view",
		"type": "function"
	},
	{
		"inputs": [],
		"name": "allTokenNum",
		"outputs": [
			{
				"internalType": "uint256",
				"name": "",
				"type": "uint256"
			}
		],
		"stateMutability": "view",
		"type": "function"
	},
	{
		"inputs": [],
		"name": "award",
		"outputs": [
			{
				"internalType": "uint256",
				"name": "",
				"type": "uint256"
			}
		],
		"stateMutability": "view",
		"type": "function"
	},
	{
		"inputs": [],
		"name": "checkRate",
		"outputs": [
			{
				"internalType": "uint256",
				"name": "",
				"type": "uint256"
			}
		],
		"stateMutability": "view",
		"type": "function"
	},
	{
		"inputs": [],
		"name": "controlAddress",
		"outputs": [
			{
				"internalType": "address",
				"name": "",
				"type": "address"
			}
		],
		"stateMutability": "view",
		"type": "function"
	},
	{
		"inputs": [
			{
				"internalType": "address",
				"name": "",
				"type": "address"
			}
		],
		"name": "distributionRatio",
		"outputs": [
			{
				"internalType": "uint256",
				"name": "",
				"type": "uint256"
			}
		],
		"stateMutability": "view",
		"type": "function"
	},
	{
		"inputs": [],
		"name": "firstTime",
		"outputs": [
			{
				"internalType": "uint256",
				"name": "",
				"type": "uint256"
			}
		],
		"stateMutability": "view",
		"type": "function"
	},
	{
		"inputs": [],
		"name": "getAllocationFundAddressLength",
		"outputs": [
			{
				"internalType": "uint256",
				"name": "",
				"type": "uint256"
			}
		],
		"stateMutability": "view",
		"type": "function"
	},
	{
		"inputs": [
			{
				"internalType": "uint256",
				"name": "num",
				"type": "uint256"
			},
			{
				"internalType": "uint256",
				"name": "tokenNum",
				"type": "uint256"
			}
		],
		"name": "getSourceOfIncome",
		"outputs": [
			{
				"internalType": "uint256[]",
				"name": "",
				"type": "uint256[]"
			}
		],
		"stateMutability": "view",
		"type": "function"
	},
	{
		"inputs": [
			{
				"internalType": "uint256",
				"name": "num",
				"type": "uint256"
			},
			{
				"internalType": "uint256",
				"name": "tokenNum",
				"type": "uint256"
			}
		],
		"name": "getSourceOfIncomeLength",
		"outputs": [
			{
				"internalType": "uint256",
				"name": "",
				"type": "uint256"
			}
		],
		"stateMutability": "view",
		"type": "function"
	},
	{
		"inputs": [],
		"name": "getTokenBalance",
		"outputs": [
			{
				"internalType": "uint256",
				"name": "",
				"type": "uint256"
			}
		],
		"stateMutability": "view",
		"type": "function"
	},
	{
		"inputs": [],
		"name": "getWETHBalance",
		"outputs": [
			{
				"internalType": "uint256",
				"name": "",
				"type": "uint256"
			}
		],
		"stateMutability": "view",
		"type": "function"
	},
	{
		"inputs": [],
		"name": "intervalTime",
		"outputs": [
			{
				"internalType": "uint256",
				"name": "",
				"type": "uint256"
			}
		],
		"stateMutability": "view",
		"type": "function"
	},
	{
		"inputs": [],
		"name": "owner",
		"outputs": [
			{
				"internalType": "address",
				"name": "",
				"type": "address"
			}
		],
		"stateMutability": "view",
		"type": "function"
	},
	{
		"inputs": [],
		"name": "pause",
		"outputs": [
			{
				"internalType": "bool",
				"name": "",
				"type": "bool"
			}
		],
		"stateMutability": "view",
		"type": "function"
	},
	{
		"inputs": [],
		"name": "rate",
		"outputs": [
			{
				"internalType": "uint256",
				"name": "",
				"type": "uint256"
			}
		],
		"stateMutability": "view",
		"type": "function"
	},
	{
		"inputs": [],
		"name": "Reputation",
		"outputs": [
			{
				"internalType": "address",
				"name": "",
				"type": "address"
			}
		],
		"stateMutability": "view",
		"type": "function"
	},
	{
		"inputs": [],
		"name": "ReputationAmount",
		"outputs": [
			{
				"internalType": "uint256",
				"name": "",
				"type": "uint256"
			}
		],
		"stateMutability": "view",
		"type": "function"
	},
	{
		"inputs": [
			{
				"internalType": "uint256",
				"name": "",
				"type": "uint256"
			},
			{
				"internalType": "uint256",
				"name": "",
				"type": "uint256"
			},
			{
				"internalType": "uint256",
				"name": "",
				"type": "uint256"
			}
		],
		"name": "sourceOfIncome",
		"outputs": [
			{
				"internalType": "uint256",
				"name": "",
				"type": "uint256"
			}
		],
		"stateMutability": "view",
		"type": "function"
	},
	{
		"inputs": [],
		"name": "userTime",
		"outputs": [
			{
				"internalType": "uint256",
				"name": "",
				"type": "uint256"
			}
		],
		"stateMutability": "view",
		"type": "function"
	},
	{
		"inputs": [],
		"name": "weth",
		"outputs": [
			{
				"internalType": "address",
				"name": "",
				"type": "address"
			}
		],
		"stateMutability": "view",
		"type": "function"
	}
]
